LICENSE
README.md
pyproject.toml
requirements.txt
setup.py
avsniper/__init__.py
avsniper/__main__.py
avsniper/__meta__.py
avsniper/args.py
avsniper/avsniper.py
avsniper/cmdbase.py
avsniper/config.py
avsniper/module.py
avsniper.egg-info/PKG-INFO
avsniper.egg-info/SOURCES.txt
avsniper.egg-info/dependency_links.txt
avsniper.egg-info/entry_points.txt
avsniper.egg-info/requires.txt
avsniper.egg-info/top_level.txt
avsniper/cmd/__init__.py
avsniper/cmd/auto_adjust.py
avsniper/cmd/auto_checker.py
avsniper/cmd/checker.py
avsniper/cmd/checkremote.py
avsniper/cmd/clean.py
avsniper/cmd/clone_info.py
avsniper/cmd/enumerate.py
avsniper/cmd/export_exe.py
avsniper/cmd/list.py
avsniper/cmd/multi_av.py
avsniper/cmd/showblacklist.py
avsniper/cmd/strip.py
avsniper/cmd/transfor.py
avsniper/formats/__init__.py
avsniper/formats/microsoft_pe.py
avsniper/libs/__init__.py
avsniper/libs/binary_tree.py
avsniper/libs/ca.py
avsniper/libs/mime_ext.json
avsniper/libs/pyinstaller.py
avsniper/libs/binutils/__init__.py
avsniper/libs/libmagic_windows/README.md
avsniper/libs/libmagic_windows/__init__.py
avsniper/libs/libmagic_windows/libgnurx-0.dll
avsniper/libs/libmagic_windows/magic.mgc
avsniper/libs/libmagic_windows/magic1.dll
avsniper/libs/versioninfo/__init__.py
avsniper/libs/versioninfo/exceptions.py
avsniper/libs/versioninfo/parser.py
avsniper/structs/__init__.py
avsniper/util/__init__.py
avsniper/util/color.py
avsniper/util/cursor.py
avsniper/util/database.py
avsniper/util/disassembler.py
avsniper/util/exerunner.py
avsniper/util/logger.py
avsniper/util/microsoft_pe_holder.py
avsniper/util/process.py
avsniper/util/progress.py
avsniper/util/sniperdb.py
avsniper/util/strings.py
avsniper/util/tools.py
avsniper/util/worker.py