Metadata-Version: 2.1
Name: avsniper
Version: 0.1.0
Summary: AV Sniper is a tool to strip and check binary string.
Author-email: "Helvio Junior (M4v3r1ck)" <helvio_junior@hotmail.com>
Maintainer-email: "Helvio Junior (M4v3r1ck)" <helvio_junior@hotmail.com>
License: GNU GENERAL PUBLIC LICENSE
Project-URL: Documentation, https://github.com/helviojunior/avsniper
Project-URL: Source, https://github.com/helviojunior/avsniper
Project-URL: Tracker, https://github.com/helviojunior/avsniper
Project-URL: Author, https://github.com/helviojunior
Keywords: av sniper,development,red team
Classifier: Development Status :: 4 - Beta
Classifier: Environment :: Console
Classifier: Intended Audience :: System Administrators
Classifier: License :: OSI Approved :: GNU General Public License v3 (GPLv3)
Classifier: Natural Language :: English
Classifier: Operating System :: OS Independent
Classifier: Programming Language :: Python
Classifier: Programming Language :: Python :: 3
Classifier: Programming Language :: Python :: 3.9
Classifier: Programming Language :: Python :: 3.10
Classifier: Programming Language :: Python :: 3.11
Classifier: Programming Language :: Python :: 3 :: Only
Classifier: Programming Language :: Python :: Implementation :: PyPy
Classifier: Topic :: Security
Classifier: Topic :: Utilities
Requires-Python: <4,>=3.9
License-File: LICENSE
Requires-Dist: colorama
Requires-Dist: kaitaistruct>=0.10
Requires-Dist: hexdump>=3.3
Requires-Dist: tabulate>=0.9.0
Requires-Dist: requests
Requires-Dist: python-magic>=0.4.27
Requires-Dist: python-magic-bin>=0.4.14; platform_system == "Windows"
Requires-Dist: cryptography==41.0.4
Requires-Dist: pyOpenSSL==23.2.0
Requires-Dist: asn1crypto>=1.5.1
Requires-Dist: psutil>=5.9.6
Requires-Dist: pyyaml>=5.0
Requires-Dist: setuptools>=75.2.0
